eskiz_sms/__init__.py
eskiz_sms/async_.py
eskiz_sms/base.py
eskiz_sms/enums.py
eskiz_sms/eskiz.py
eskiz_sms/exceptions.py
eskiz_sms/logging.py
eskiz_sms/request.py
eskiz_sms/token.py
eskiz_sms/types.py
eskiz_sms-0.2.5.dist-info/METADATA
eskiz_sms-0.2.5.dist-info/WHEEL
eskiz_sms-0.2.5.dist-info/RECORD
