Metadata-Version: 2.4
Name: eskiz-sms
Version: 0.2.5
Summary: Package for eskiz.uz/sms
Author: Malikov
Author-email: mlkv.dev@gmail.com
Requires-Python: >=3.8,<4.0
Classifier: Programming Language :: Python :: 3
Classifier: Programming Language :: Python :: 3.8
Classifier: Programming Language :: Python :: 3.9
Classifier: Programming Language :: Python :: 3.10
Classifier: Programming Language :: Python :: 3.11
Classifier: Programming Language :: Python :: 3.12
Classifier: Programming Language :: Python :: 3.13
Classifier: Programming Language :: Python :: 3.14
Requires-Dist: httpx (>=0.28.1,<0.29.0)
Requires-Dist: python-dotenv (>=1.0.0,<2.0.0)
Project-URL: Homepage, https://github.com/malikovss/eskiz-sms
